{
	"configurations" : 
	[
		{
			"directories" : 
			[
				{
					"build" : ".",
					"minimumCMakeVersion" : 
					{
						"string" : "3.6.0"
					},
					"projectIndex" : 0,
					"source" : "."
				}
			],
			"name" : "RelWithDebInfo",
			"projects" : 
			[
				{
					"directoryIndexes" : 
					[
						0
					],
					"name" : "Project"
				}
			],
			"targets" : []
		}
	],
	"kind" : "codemodel",
	"paths" : 
	{
		"build" : "/Users/changyoung/Desktop/공공데이터/cnumap/frontend/moducnu/android/app/.cxx/RelWithDebInfo/3p6y5a4z/arm64-v8a",
		"source" : "/Users/changyoung/flutter/packages/flutter_tools/gradle/src/main/groovy"
	},
	"version" : 
	{
		"major" : 2,
		"minor" : 1
	}
}
